THEREMIN/midi_note_sender.v
module midi_note_sender (
    input clk,
    input rst,
    input [15:0] distance_cm,
    input distance_ready,
    output reg [7:0] midi_byte,
    output reg midi_send,
    input uart_ready
);
    reg [1:0] state;
    localparam IDLE = 2'b00,
               SEND1 = 2'b01,
               SEND2 = 2'b10,
               SEND3 = 2'b11;

    reg [7:0] note;

    always @(posedge clk or posedge rst) begin
        if (rst) begin
            state <= IDLE;
            midi_byte <= 0;
            midi_send <= 0;
        end else begin
            midi_send <= 0;
            case (state)
                IDLE: begin
                    if (distance_ready) begin
                        note <= (distance_cm < 5) ? 80 :
                                (distance_cm > 60) ? 50 :
                                80 - ((distance_cm - 5) * 30 / 55);
                        state <= SEND1;
                    end
                end
                SEND1: if (uart_ready) begin midi_byte <= 8'h90; midi_send <= 1; state <= SEND2; end
                SEND2: if (uart_ready) begin midi_byte <= note;  midi_send <= 1; state <= SEND3; end
                SEND3: if (uart_ready) begin midi_byte <= 8'd100; midi_send <= 1; state <= IDLE; end
            endcase
        end
    end
endmodule

THEREMIN/midi_note_sender_tb.v
`timescale 1ns/1ps

module midi_note_sender_tb;

    reg clk = 0;
    reg rst = 1;
    reg [15:0] distance_cm = 0;
    reg distance_ready = 0;
    wire [7:0] midi_byte;
    wire midi_send;
    reg uart_ready = 1;

    // Instancia del módulo a probar
    midi_note_sender uut (
        .clk(clk),
        .rst(rst),
        .distance_cm(distance_cm),
        .distance_ready(distance_ready),
        .midi_byte(midi_byte),
        .midi_send(midi_send),
        .uart_ready(uart_ready)
    );

    // Generación de reloj (10ns periodo)
    always #5 clk = ~clk;

    initial begin
        $dumpfile("midi_note_sender.vcd");       // Archivos de señales
        $dumpvars(0, midi_note_sender_tb);       // Captura todas las señales del testbench

        // Reset inicial
        #10 rst = 0;

        // Primer evento: se mide una distancia válida
        #10 distance_cm = 20;
            distance_ready = 1;
        #10 distance_ready = 0;

        // Segundo evento: otra distancia
        #100 distance_cm = 55;
             distance_ready = 1;
        #10  distance_ready = 0;

        // Esperar un poco más
        #100;

        $finish;
    end

endmodule

THEREMIN/midi_note_sender.vcd
$date
	Sun Jul 20 23:57:51 2025
$end
$version
	Icarus Verilog
$end
$timescale
	1ps
$end
$scope module midi_note_sender_tb $end
$var wire 1 ! midi_send $end
$var wire 8 " midi_byte [7:0] $end
$var reg 1 # clk $end
$var reg 16 $ distance_cm [15:0] $end
$var reg 1 % distance_ready $end
$var reg 1 & rst $end
$var reg 1 ' uart_ready $end
$scope module uut $end
$var wire 1 # clk $end
$var wire 16 ( distance_cm [15:0] $end
$var wire 1 % distance_ready $end
$var wire 1 & rst $end
$var wire 1 ' uart_ready $end
$var parameter 2 ) IDLE $end
$var parameter 2 * SEND1 $end
$var parameter 2 + SEND2 $end
$var parameter 2 , SEND3 $end
$var reg 8 - midi_byte [7:0] $end
$var reg 1 ! midi_send $end
$var reg 8 . note [7:0] $end
$var reg 2 / state [1:0] $end
$upscope $end
$upscope $end
$enddefinitions $end
$comment Show the parameter values. $end
$dumpall
b11 ,
b10 +
b1 *
b0 )
$end
#0
$dumpvars
b0 /
bx .
b0 -
b0 (
1'
1&
0%
b0 $
0#
b0 "
0!
$end
#5000
1#
#10000
0#
0&
#15000
1#
#20000
0#
1%
b10100 $
b10100 (
#25000
b1 /
b1001000 .
1#
#30000
0#
0%
#35000
b10 /
1!
b10010000 "
b10010000 -
1#
#40000
0#
#45000
b11 /
b1001000 "
b1001000 -
1!
1#
#50000
0#
#55000
b0 /
b1100100 "
b1100100 -
1!
1#
#60000
0#
#65000
0!
1#
#70000
0#
#75000
1#
#80000
0#
#85000
1#
#90000
0#
#95000
1#
#100000
0#
#105000
1#
#110000
0#
#115000
1#
#120000
0#
#125000
1#
#130000
0#
1%
b110111 $
b110111 (
#135000
b1 /
b110101 .
1#
#140000
0#
0%
#145000
b10 /
1!
b10010000 "
b10010000 -
1#
#150000
0#
#155000
b11 /
b110101 "
b110101 -
1!
1#
#160000
0#
#165000
b0 /
b1100100 "
b1100100 -
1!
1#
#170000
0#
#175000
0!
1#
